setup.py
tinycms/__init__.py
tinycms/admin.py
tinycms/models.py
tinycms/tests.py
tinycms/urls.py
tinycms/views.py
tinycms.egg-info/PKG-INFO
tinycms.egg-info/SOURCES.txt
tinycms.egg-info/dependency_links.txt
tinycms.egg-info/entry_points.txt
tinycms.egg-info/not-zip-safe
tinycms.egg-info/requires.txt
tinycms.egg-info/top_level.txt
tinycms/migrations/0001_initial.py
tinycms/migrations/0002_auto_20141030_2250.py
tinycms/migrations/0003_auto_20141115_1828.py
tinycms/migrations/0004_auto_20141117_2225.py
tinycms/migrations/__init__.py
tinycms/templatetags/__init__.py
tinycms/templatetags/tinycms_tags.py