Metadata-Version: 1.1
Name: tinycms
Version: 0.4.3
Summary: Simple CMS for django
Home-page: https://www.whiteblack-cat.info/
Author: ccat
Author-email: UNKNOWN
License: MIT
Platform: UNKNOWN
Classifier: Framework :: Django
Classifier: License :: OSI Approved :: MIT License
Classifier: Programming Language :: Python
